LICENSE.md
MANIFEST.in
README.md
clean.sh
setup.py
GRIDOPT.egg-info/PKG-INFO
GRIDOPT.egg-info/SOURCES.txt
GRIDOPT.egg-info/dependency_links.txt
GRIDOPT.egg-info/entry_points.txt
GRIDOPT.egg-info/not-zip-safe
GRIDOPT.egg-info/requires.txt
GRIDOPT.egg-info/top_level.txt
docs/Makefile
docs/conf.py
docs/defs.hrst
docs/index.rst
docs/power_flow.rst
docs/reference.rst
docs/script.rst
docs/start.rst
docs/_templates/layout.html
examples/dcopf.py
examples/methods.py
examples/start.py
gridopt/__init__.py
gridopt/version.py
gridopt/power_flow/__init__.py
gridopt/power_flow/ac_opf.py
gridopt/power_flow/ac_pf.py
gridopt/power_flow/dc_opf.py
gridopt/power_flow/dc_pf.py
gridopt/power_flow/method.py
gridopt/power_flow/method_error.py
gridopt/scripts/__init__.py
gridopt/scripts/gridopt.py
tests/__init__.py
tests/test_power_flow.py
tests/test_scripts.py
tests/utils.py
tests/resources/cases/case118.mat
tests/resources/cases/case1354.mat
tests/resources/cases/case2869.mat
tests/resources/cases/case300.mat
tests/resources/cases/case3012wp.mat
tests/resources/cases/case3375wp.mat
tests/resources/cases/case39.mat
tests/resources/cases/case89.mat
tests/resources/cases/case9.mat
tests/resources/cases/case9241.mat
tests/resources/cases/ieee14.m
tests/resources/cases/ieee25.m
tests/resources/cases/ieee300.mat
tests/resources/pf_solutions/case3012wp.mat.sol1
tests/resources/pf_solutions/case3012wp.mat.sol2
tests/resources/pf_solutions/ieee14.mat.sol1