Metadata-Version: 1.1
Name: GRIDOPT
Version: 1.3.6rc1
Summary: Power Grid Optimization Library
Home-page: https://github.com/ttinoco/GRIDOPT
Author: Tomas Tinoco De Rubira
Author-email: ttinoco5687@gmail.com
License: BSD 2-Clause License
Platform: UNKNOWN
Classifier: Development Status :: 5 - Production/Stable
Classifier: License :: OSI Approved :: BSD License
Classifier: Programming Language :: Python :: 2.7
Classifier: Programming Language :: Python :: 3.5
